{"name":"libisabelle","tagline":"A Scala library which talks to Isabelle","body":"`libisabelle` is a Scala library providing principled access to the [Isabelle](https://isabelle.in.tum.de) proof assistant. Notable features include:\r\n\r\n- (mostly) asynchronous API\r\n- prover interaction abstracted into typed, atomic operations\r\n- automatic installation of Isabelle\r\n- multi-version and multi-tenancy support","google":"","note":"Don't delete this file! It's used internally to help with page regeneration."}